all_repos/__init__.py
all_repos/autofix_lib.py
all_repos/bitbucket_api.py
all_repos/bitbucket_server_api.py
all_repos/cli.py
all_repos/clone.py
all_repos/color.py
all_repos/complete.py
all_repos/config.py
all_repos/find_files.py
all_repos/git.py
all_repos/github_api.py
all_repos/gitlab_api.py
all_repos/grep.py
all_repos/list_repos.py
all_repos/manual.py
all_repos/mapper.py
all_repos/sed.py
all_repos/util.py
all_repos/autofix/__init__.py
all_repos/autofix/_pre_commit_hook_migrate.py
all_repos/autofix/azure_pipelines_autoupdate.py
all_repos/autofix/pre_commit_autopep8_migrate.py
all_repos/autofix/pre_commit_autoupdate.py
all_repos/autofix/pre_commit_cache_dir.py
all_repos/autofix/pre_commit_flake8_migrate.py
all_repos/autofix/pre_commit_migrate_config.py
all_repos/autofix/setup_py_upgrade.py
all_repos/push/__init__.py
all_repos/push/azure_repos_pull_request.py
all_repos/push/bitbucket_server_pull_request.py
all_repos/push/github_pull_request.py
all_repos/push/gitlab_pull_request.py
all_repos/push/merge_to_master.py
all_repos/push/readonly.py
all_repos/source/__init__.py
all_repos/source/azure_repos.py
all_repos/source/bitbucket.py
all_repos/source/bitbucket_server.py
all_repos/source/github.py
all_repos/source/github_forks.py
all_repos/source/github_org.py
all_repos/source/gitlab_org.py
all_repos/source/gitolite.py
all_repos/source/json_file.py
all_repos-1.31.0.dist-info/LICENSE
all_repos-1.31.0.dist-info/METADATA
all_repos-1.31.0.dist-info/WHEEL
all_repos-1.31.0.dist-info/entry_points.txt
all_repos-1.31.0.dist-info/top_level.txt
all_repos-1.31.0.dist-info/RECORD
