Metadata-Version: 2.1
Name: all_repos
Version: 1.31.0
Summary: Clone all your repositories and apply sweeping changes.
Home-page: https://github.com/asottile/all-repos
Author: Anthony Sottile
Author-email: asottile@umich.edu
License: MIT
Classifier: Programming Language :: Python :: 3
Classifier: Programming Language :: Python :: 3 :: Only
Classifier: Programming Language :: Python :: Implementation :: CPython
Requires-Python: >=3.10
License-File: LICENSE
Requires-Dist: identify
Requires-Dist: packaging>=20.9
Requires-Dist: contextlib-chdir; python_version < "3.11"
